safegcd/__init__.py
safegcd/core.py
safegcd-0.1.0.dist-info/METADATA
safegcd-0.1.0.dist-info/WHEEL
safegcd-0.1.0.dist-info/top_level.txt
safegcd-0.1.0.dist-info/RECORD
