Metadata-Version: 2.4
Name: safegcd
Version: 0.1.0
Summary: Minimal divstep primitive for safegcd/Bernstein–Yang style experiments
Author: Cesare Huang
License-Expression: MIT
Keywords: cryptography,number-theory,gcd,divstep,safegcd
Classifier: Programming Language :: Python :: 3
Requires-Python: >=3.10
